devtools_json_path/__init__.py
devtools_json_path-1.0.1.dist-info/METADATA
devtools_json_path-1.0.1.dist-info/WHEEL
devtools_json_path-1.0.1.dist-info/top_level.txt
devtools_json_path-1.0.1.dist-info/RECORD
