Metadata-Version: 2.1
Name: devtools_json_path
Version: 1.0.1
Summary: JSONPath tester
Home-page: https://devtools.at/tools/json-path-tester
Author: DevTools.at
Author-email: hello@devtools.at
Project-URL: Homepage, https://devtools.at/tools/json-path-tester
Project-URL: Repository, https://github.com/devtools-at/json-path-tester
Classifier: Development Status :: 4 - Beta
Classifier: Intended Audience :: Developers
Classifier: License :: OSI Approved :: MIT License
Classifier: Programming Language :: Python :: 3
Requires-Python: >=3.8
